pythonmonkey/__init__.py
pythonmonkey/builtin_modules/XMLHttpRequest-internal.d.ts
pythonmonkey/builtin_modules/XMLHttpRequest-internal.py
pythonmonkey/builtin_modules/XMLHttpRequest.js
pythonmonkey/builtin_modules/base64.d.ts
pythonmonkey/builtin_modules/base64.py
pythonmonkey/builtin_modules/console.js
pythonmonkey/builtin_modules/dom-exception.d.ts
pythonmonkey/builtin_modules/dom-exception.js
pythonmonkey/builtin_modules/event-target.js
pythonmonkey/builtin_modules/internal-binding.d.ts
pythonmonkey/builtin_modules/internal-binding.py
pythonmonkey/builtin_modules/timers.js
pythonmonkey/builtin_modules/url.d.ts
pythonmonkey/builtin_modules/url.js
pythonmonkey/builtin_modules/util.js
pythonmonkey/cli/__init__.py
pythonmonkey/cli/pmjs.py
pythonmonkey/global.d.ts
pythonmonkey/helpers.py
pythonmonkey/lib/pmdb.py
pythonmonkey/lib/pmjs/global-init.js
pythonmonkey/lib/wtfpm.py
pythonmonkey/libmozjs-136a1.dylib
pythonmonkey/py.typed
pythonmonkey/pythonmonkey.pyi
pythonmonkey/pythonmonkey.so
pythonmonkey/require.py
pythonmonkey/tsconfig.json
pythonmonkey_fork-1.3.0.dist-info/LICENSE
pythonmonkey_fork-1.3.0.dist-info/METADATA
pythonmonkey_fork-1.3.0.dist-info/WHEEL
pythonmonkey_fork-1.3.0.dist-info/entry_points.txt
pythonmonkey_fork-1.3.0.dist-info/RECORD
