Metadata-Version: 2.1
Name: pythonmonkey-fork
Version: 1.3.0
Summary: Seamless interop between Python and JavaScript.
Home-page: https://pythonmonkey.io/
License: MIT
Author: Distributive Corp.
Author-email: pm@distributive.network
Requires-Python: >=3.8,<4.0
Classifier: License :: OSI Approved :: MIT License
Classifier: Programming Language :: Python :: 3
Classifier: Programming Language :: Python :: 3.8
Classifier: Programming Language :: Python :: 3.9
Classifier: Programming Language :: Python :: 3.10
Classifier: Programming Language :: Python :: 3.11
Requires-Dist: aiohttp[speedups] (>=3.9.5,<4.0.0)
Requires-Dist: pythonmonkey-node-modules (~=0.1)
Requires-Dist: pyreadline3 (>=3.4.1,<4.0.0) ; sys_platform == "win32"
Project-URL: Documentation, https://docs.pythonmonkey.io/
Project-URL: Repository, https://github.com/Distributive-Network/PythonMonkey
